hypersync_lancedb_pipe/__init__.py
hypersync_lancedb_pipe/db_manager.py
hypersync_lancedb_pipe-0.1.1.dist-info/METADATA
hypersync_lancedb_pipe-0.1.1.dist-info/WHEEL
hypersync_lancedb_pipe-0.1.1.dist-info/RECORD
