Metadata-Version: 2.3
Name: hypersync-lancedb-pipe
Version: 0.1.1
Summary: A serverless embedded streaming OLAP data pipeline
Author-email: Evan K <ekcopersonal@gmail.com>
Requires-Python: >=3.8
Requires-Dist: boto3>=1.34.94
Requires-Dist: duckdb>=0.10.2
Requires-Dist: hvplot>=0.9.2
Requires-Dist: hypersync==0.6.1
Requires-Dist: ipykernel>=6.29.4
Requires-Dist: lancedb>=0.6.11
Requires-Dist: polars>=0.20.23
Requires-Dist: pyarrow==15.0.0
